cwl_inputs_parser/__init__.py
cwl_inputs_parser/main.py
cwl_inputs_parser/server.py
cwl_inputs_parser/utils.py
cwl_inputs_parser-1.0.2.data/data/LICENSE
cwl_inputs_parser-1.0.2.data/data/README.md
cwl_inputs_parser-1.0.2.data/data/cwl-inputs-parser-schema.json
cwl_inputs_parser-1.0.2.dist-info/LICENSE
cwl_inputs_parser-1.0.2.dist-info/METADATA
cwl_inputs_parser-1.0.2.dist-info/WHEEL
cwl_inputs_parser-1.0.2.dist-info/entry_points.txt
cwl_inputs_parser-1.0.2.dist-info/top_level.txt
cwl_inputs_parser-1.0.2.dist-info/RECORD
