Metadata-Version: 2.1
Name: cwl-inputs-parser
Version: 1.0.2
Summary: The parser of inputs field in Common Workflow Language (CWL)
Home-page: https://github.com/suecharo/cwl-inputs-parser
Author: suecharo
Author-email: suehiro619@gmail.com
License: Apache 2.0
Classifier: Development Status :: 5 - Production/Stable
Classifier: Framework :: Flask
Classifier: Intended Audience :: Healthcare Industry
Classifier: Intended Audience :: Information Technology
Classifier: Intended Audience :: Science/Research
Classifier: License :: OSI Approved :: Apache Software License
Classifier: Programming Language :: Python :: 3
Classifier: Programming Language :: Python :: 3 :: Only
Classifier: Programming Language :: Python :: 3.6
Classifier: Programming Language :: Python :: 3.7
Classifier: Programming Language :: Python :: 3.8
Classifier: Programming Language :: Python :: 3.9
Classifier: Topic :: Scientific/Engineering
Classifier: Topic :: Scientific/Engineering :: Bio-Informatics
Requires-Python: >=3.6
License-File: LICENSE
Requires-Dist: cwl-utils
Requires-Dist: flask
Requires-Dist: pyyaml
Requires-Dist: requests
Requires-Dist: cwltool
Requires-Dist: ruamel.yaml
Provides-Extra: testing
Requires-Dist: flake8 ; extra == 'testing'
Requires-Dist: isort ; extra == 'testing'
Requires-Dist: jsonschema ; extra == 'testing'
Requires-Dist: mypy ; extra == 'testing'
Requires-Dist: pytest ; extra == 'testing'
Requires-Dist: types-PyYAML ; extra == 'testing'
Requires-Dist: types-requests ; extra == 'testing'
Requires-Dist: types-setuptools ; extra == 'testing'
